opentelemetry/instrumentation/anthropic/__init__.py
opentelemetry/instrumentation/anthropic/config.py
opentelemetry/instrumentation/anthropic/event_emitter.py
opentelemetry/instrumentation/anthropic/event_models.py
opentelemetry/instrumentation/anthropic/span_utils.py
opentelemetry/instrumentation/anthropic/streaming.py
opentelemetry/instrumentation/anthropic/utils.py
opentelemetry/instrumentation/anthropic/version.py
moda_anthropic-0.1.0.dist-info/METADATA
moda_anthropic-0.1.0.dist-info/WHEEL
moda_anthropic-0.1.0.dist-info/entry_points.txt
moda_anthropic-0.1.0.dist-info/RECORD
