Metadata-Version: 2.4
Name: moda-anthropic
Version: 0.1.0
Summary: Moda Anthropic instrumentation for LLM observability
Project-URL: Repository, https://github.com/ModaLabs/moda-python/tree/main/packages/moda-anthropic
Author-email: Moda Labs <support@moda.so>
License-Expression: Apache-2.0
Requires-Python: <4,>=3.10
Requires-Dist: opentelemetry-api<2,>=1.38.0
Requires-Dist: opentelemetry-instrumentation>=0.59b0
Requires-Dist: opentelemetry-semantic-conventions-ai<0.5.0,>=0.4.13
Requires-Dist: opentelemetry-semantic-conventions>=0.59b0
Provides-Extra: instruments
Requires-Dist: anthropic; extra == 'instruments'
